{
    "qitianxia": {
        "action": 1,
        "res": 1,
        "data": {
            "count": 1,
            "rank": [{
                "user": {
                    "username": "wanwan",
                    "userid": 306571,
                    "avatar": "http://static.imxingzhe.com/photo/306571/xingzhe/1438934663089.jpg"
                },
                "value": 123.1
            }, {
                "user": {
                    "username": "wanwan1",
                    "userid": 306572,
                    "avatar": "http://static.imxingzhe.com/photo/306571/xingzhe/1438934663089.jpg"
                },
                "value": 124
            }, {
                "user": {
                    "username": "wanwan2",
                    "userid": 306573,
                    "avatar": "http://static.imxingzhe.com/photo/306571/xingzhe/1438934663089.jpg"
                },
                "value": 125
            }, {
                "user": {
                    "username": "wanwan3aefrgrthytjtstjhytsdgrthtyjukuik",
                    "userid": 306574,
                    "avatar": "http://q.qlogo.cn/qqapp/100921259/ED02A6C8388982AF9F9A1CC84A7E2D20/100"
                },
                "value": 126
            }],
            "total_value": 210355102
        }
    }
}
